{
    "version": "0.22.2",
    "description": "The glamourous AI coding agent for your favourite terminal",
    "homepage": "https://charm.sh/crush",
    "license": "FSL-1.1-MIT",
    "architecture": {
        "64bit": {
            "url": "https://github.com/charmbracelet/crush/releases/download/v0.22.2/crush_0.22.2_Windows_x86_64.zip",
            "hash": "6c6625479f43f8deacac64dcc35b643b22d144f27ecc568362aff506f7d65b95",
            "extract_dir": "crush_0.22.2_Windows_x86_64"
        },
        "32bit": {
            "url": "https://github.com/charmbracelet/crush/releases/download/v0.22.2/crush_0.22.2_Windows_i386.zip",
            "hash": "82dfd3d2293df2974468cfcaf5040facfa5e92cc192ddf273c59a204918a45b8",
            "extract_dir": "crush_0.22.2_Windows_i386"
        },
        "arm64": {
            "url": "https://github.com/charmbracelet/crush/releases/download/v0.22.2/crush_0.22.2_Windows_arm64.zip",
            "hash": "85e85da4bad645ad7bd8e5d8967566ab084e03ea5a31ca56d0faf03f7af6476d",
            "extract_dir": "crush_0.22.2_Windows_arm64"
        }
    },
    "bin": "crush.exe",
    "checkver": {
        "github": "https://github.com/charmbracelet/crush"
    },
    "autoupdate": {
        "architecture": {
            "64bit": {
                "url": "https://github.com/charmbracelet/crush/releases/download/v$version/crush_$version_Windows_x86_64.zip",
                "extract_dir": "crush_$version_Windows_x86_64"
            },
            "32bit": {
                "url": "https://github.com/charmbracelet/crush/releases/download/v$version/crush_$version_Windows_i386.zip",
                "extract_dir": "crush_$version_Windows_i386"
            },
            "arm64": {
                "url": "https://github.com/charmbracelet/crush/releases/download/v$version/crush_$version_Windows_arm64.zip",
                "extract_dir": "crush_$version_Windows_arm64"
            }
        },
        "hash": {
            "url": "$baseurl/checksums.txt"
        }
    }
}
