{
    "version": "0.39.0",
    "description": "The glamourous AI coding agent for your favourite terminal",
    "homepage": "https://charm.sh/crush",
    "license": "FSL-1.1-MIT",
    "architecture": {
        "64bit": {
            "url": "https://github.com/charmbracelet/crush/releases/download/v0.39.0/crush_0.39.0_Windows_x86_64.zip",
            "hash": "d1b11ea85fdba3fbb170593fc26c24dad09f847a98019df95c6e7e814b780bb9",
            "extract_dir": "crush_0.39.0_Windows_x86_64"
        },
        "32bit": {
            "url": "https://github.com/charmbracelet/crush/releases/download/v0.39.0/crush_0.39.0_Windows_i386.zip",
            "hash": "58a86582d51a83c8cb7f4ac622fb1bf8e44e0dd1d1aeec02b60dd9389c6f92d0",
            "extract_dir": "crush_0.39.0_Windows_i386"
        },
        "arm64": {
            "url": "https://github.com/charmbracelet/crush/releases/download/v0.39.0/crush_0.39.0_Windows_arm64.zip",
            "hash": "9b502fe41d1f2e5c96aa17a52a6cd87b75e4a941b2afd0638e584a62fd03b6a0",
            "extract_dir": "crush_0.39.0_Windows_arm64"
        }
    },
    "bin": "crush.exe",
    "checkver": {
        "github": "https://github.com/charmbracelet/crush"
    },
    "autoupdate": {
        "architecture": {
            "64bit": {
                "url": "https://github.com/charmbracelet/crush/releases/download/v$version/crush_$version_Windows_x86_64.zip",
                "extract_dir": "crush_$version_Windows_x86_64"
            },
            "32bit": {
                "url": "https://github.com/charmbracelet/crush/releases/download/v$version/crush_$version_Windows_i386.zip",
                "extract_dir": "crush_$version_Windows_i386"
            },
            "arm64": {
                "url": "https://github.com/charmbracelet/crush/releases/download/v$version/crush_$version_Windows_arm64.zip",
                "extract_dir": "crush_$version_Windows_arm64"
            }
        },
        "hash": {
            "url": "$baseurl/checksums.txt"
        }
    }
}
