{
    "version": "6.5.2",
    "description": "Personal media library manager with real-time streaming and anime support.",
    "homepage": "https://github.com/RockinChaos/Shiru",
    "license": "GPL-3.0-only",
    "url": "https://github.com/RockinChaos/Shiru/releases/download/v6.5.2/win-Shiru-v6.5.2-portable.exe#/Shiru.exe",
    "hash": "45e0bd877fab539b14da8817f15732d704d5be3cfa72c012f81f89395dfe0688",
    "bin": "Shiru.exe",
    "shortcuts": [
        [
            "Shiru.exe",
            "Shiru"
        ]
    ],
    "checkver": {
        "url": "https://github.com/RockinChaos/Shiru/releases/latest/download/latest.yml",
        "regex": "version:\\s*([\\d.]+)",
        "replace": "$1"
    },
    "autoupdate": {
        "url": "https://github.com/RockinChaos/Shiru/releases/download/v$version/win-Shiru-v$version-portable.exe#/Shiru.exe"
    }
}
