{
    "version": "2025.09.19.202303",
    "description": "yt-dlp master builds",
    "homepage": "https://github.com/yt-dlp/yt-dlp-master-builds",
    "license": "Unlicense",
    "suggest": {
        "ffmpeg": "versions/ffmpeg-yt-dlp"
    },
    "architecture": {
        "64bit": {
            "url": "https://github.com/yt-dlp/yt-dlp-master-builds/releases/download/2025.09.19.202303/yt-dlp.exe",
            "hash": "a02697140ce853f64702c889f606492254f74d5eb6afa4eec002ed003e20b3c1"
        },
        "32bit": {
            "url": "https://github.com/yt-dlp/yt-dlp-master-builds/releases/download/2025.09.19.202303/yt-dlp_x86.exe#/yt-dlp.exe",
            "hash": "bb868d5c879eef316249d91dbb78a20fd18c41a8cad4e24dd94c6643d73c2a12"
        }
    },
    "bin": "yt-dlp.exe",
    "pre_install": "$null = if (!(Test-Path \"$persist_dir/yt-dlp.conf\")) { New-Item \"$dir/yt-dlp.conf\" }",
    "persist": [
        "yt-dlp.conf",
        "ytdlp_plugins",
        "yt-dlp-plugins"
    ],
    "checkver": "github",
    "autoupdate": {
        "architecture": {
            "64bit": {
                "url": "https://github.com/yt-dlp/yt-dlp-master-builds/releases/download/$version/yt-dlp.exe"
            },
            "32bit": {
                "url": "https://github.com/yt-dlp/yt-dlp-master-builds/releases/download/$version/yt-dlp_x86.exe#/yt-dlp.exe"
            }
        },
        "hash": {
            "url": "$baseurl/SHA2-256SUMS"
        }
    }
}
