{
    "version": "2025.11.29.232949",
    "description": "yt-dlp nightly builds",
    "homepage": "https://github.com/yt-dlp/yt-dlp-nightly-builds",
    "license": "Unlicense",
    "suggest": {
        "ffmpeg": "versions/ffmpeg-yt-dlp"
    },
    "architecture": {
        "64bit": {
            "url": "https://github.com/yt-dlp/yt-dlp-nightly-builds/releases/download/2025.11.29.232949/yt-dlp.exe",
            "hash": "b8c7394e06a5ed6b1b8f151918e91b67d48a75b041154144b32c6a6d9024c167"
        },
        "32bit": {
            "url": "https://github.com/yt-dlp/yt-dlp-nightly-builds/releases/download/2025.11.29.232949/yt-dlp_x86.exe#/yt-dlp.exe",
            "hash": "dd4c30c108c586035f1dc59f99aba17495f5d16b30818ce9ff08631fdba7923c"
        }
    },
    "bin": "yt-dlp.exe",
    "pre_install": "$null = if (!(Test-Path \"$persist_dir/yt-dlp.conf\")) { New-Item \"$dir/yt-dlp.conf\" }",
    "persist": [
        "yt-dlp.conf",
        "ytdlp_plugins",
        "yt-dlp-plugins"
    ],
    "checkver": "github",
    "autoupdate": {
        "architecture": {
            "64bit": {
                "url": "https://github.com/yt-dlp/yt-dlp-nightly-builds/releases/download/$version/yt-dlp.exe"
            },
            "32bit": {
                "url": "https://github.com/yt-dlp/yt-dlp-nightly-builds/releases/download/$version/yt-dlp_x86.exe#/yt-dlp.exe"
            }
        },
        "hash": {
            "url": "$baseurl/SHA2-256SUMS"
        }
    }
}
